{ "data": [ { "name": "他是谁", "pic": "http://www.itvbox.cc/云you盒/轮播图/他是谁.jpg", "url": "", "type": "search", "desc": "1988年，刑警卫国平（张译 饰）在追捕连环谜案的行动中目睹战友牺牲....", "show": true }, { "name": "长月烬明", "pic": "http://www.itvbox.cc/云you盒/轮播图/长月烬明.jpg", "url": "", "type": "search", "desc": "为了解救被魔神澹台烬（罗云熙 饰）统治折磨的...", "show": true }, { "name": "看见缘分的的少女", "pic": "http://www.itvbox.cc/云you盒/轮播图/看见缘分的少女.jpg", "url": "", "type": "search", "desc": "不能动情的异能少女帮天生克妻命的恨嫁小侯爷结缘，结果却搭上了自己...", "show": true }, { "name": "深海", "pic": "http://www.itvbox.cc/云you盒/轮播图/深海.jpg", "url": "", "type": "search", "desc": "在大海的最深处，藏着所有秘密。一位现代少女（参宿）误入梦幻的深海世界...", "show": true } ] }
